{"PrefabResourceLocation":"Prefabs/Ball2","ExtraData":[{"_constraints":0,"_velocity":[0.0,0.0,0.0],"_rotation":[0.0,0.0,0.0],"IsKinematic":false,"DataType":"Rigidbody","GUID":"28f9765b-d68b-46c4-b04c-a34912dbcc21"},{"_position":[494.422119,0.329658777,504.390717],"_rotation":[0.0,0.0,-0.300130427,0.9538982],"_scale":[0.00229658652,0.00229658652,0.00229658652],"GUID":"8b6af1e9-3313-4edb-9a51-4ee80c1331b7","DataType":"Location"},{"Price":1.99,"Name":"Brain Ball","Description":"Playing with this will make your pet smarter. We think.","DataType":"ShopItem","GUID":"7cdb6b2a-804e-4830-9312-42270e8d191a"}],"GUID":null}